flowket/__init__.py
flowket/main.py
flowket/callbacks/__init__.py
flowket/callbacks/checkpoint.py
flowket/callbacks/tensorboard.py
flowket/callbacks/exact/__init__.py
flowket/callbacks/exact/local_energy.py
flowket/callbacks/exact/machine_updated.py
flowket/callbacks/exact/observable.py
flowket/callbacks/exact/runtime_stats.py
flowket/callbacks/exact/sigma_z.py
flowket/callbacks/monte_carlo/__init__.py
flowket/callbacks/monte_carlo/bad_eigen_state_stopping.py
flowket/callbacks/monte_carlo/generator_iterator.py
flowket/callbacks/monte_carlo/local_energy_stats.py
flowket/callbacks/monte_carlo/mcmc_stats.py
flowket/callbacks/monte_carlo/observable.py
flowket/callbacks/monte_carlo/runtime_stats.py
flowket/callbacks/monte_carlo/tensorboard_with_generator_validation_data.py
flowket/deepar/__init__.py
flowket/deepar/graph_analysis/__init__.py
flowket/deepar/graph_analysis/concatenate_topology.py
flowket/deepar/graph_analysis/convolutional_topology.py
flowket/deepar/graph_analysis/data_structures.py
flowket/deepar/graph_analysis/dependency_graph.py
flowket/deepar/graph_analysis/gathering_topology.py
flowket/deepar/graph_analysis/layer_topology.py
flowket/deepar/graph_analysis/masking_topology.py
flowket/deepar/graph_analysis/one_to_one_topology.py
flowket/deepar/graph_analysis/padding_topology.py
flowket/deepar/graph_analysis/reshape_topology.py
flowket/deepar/graph_analysis/sampling_topology.py
flowket/deepar/graph_analysis/topology_manager.py
flowket/deepar/layers/__init__.py
flowket/deepar/layers/autoregressive.py
flowket/deepar/layers/casting.py
flowket/deepar/layers/gathering.py
flowket/deepar/layers/lambda_with_one_to_one_topology.py
flowket/deepar/layers/layer_normalization.py
flowket/deepar/layers/masking.py
flowket/deepar/layers/one_hot.py
flowket/deepar/layers/padding.py
flowket/deepar/layers/wrappers.py
flowket/deepar/ordering/__init__.py
flowket/deepar/ordering/flat.py
flowket/deepar/ordering/moves.py
flowket/deepar/ordering/raster.py
flowket-0.2.3.dist-info/LICENSE
flowket-0.2.3.dist-info/METADATA
flowket-0.2.3.dist-info/WHEEL
flowket-0.2.3.dist-info/top_level.txt
flowket-0.2.3.dist-info/RECORD
